bdsf/__init__.py
bdsf/_cbdsm.cpython-313-x86_64-linux-gnu.so
bdsf/_changelog.py
bdsf/_pytesselate.cpython-313-x86_64-linux-gnu.so
bdsf/_version.py
bdsf/cleanup.py
bdsf/collapse.py
bdsf/const.py
bdsf/functions.py
bdsf/gaul2srl.py
bdsf/gausfit.py
bdsf/image.py
bdsf/interface.py
bdsf/islands.py
bdsf/make_residimage.py
bdsf/multi_proc.py
bdsf/mylogger.py
bdsf/opts.py
bdsf/output.py
bdsf/plotresults.py
bdsf/polarisation.py
bdsf/preprocess.py
bdsf/psf_vary.py
bdsf/pybdsf.py
bdsf/readimage.py
bdsf/rmsimage.py
bdsf/shapefit.py
bdsf/shapelets.py
bdsf/sourcecounts.py
bdsf/spectralindex.py
bdsf/statusbar.py
bdsf/tc.py
bdsf/threshold.py
bdsf/wavelet_atrous.py
bdsf/nat/__init__.py
bdsf/nat/natgridmodule.cpython-313-x86_64-linux-gnu.so
bdsf.libs/libboost_container-9991264c.so.1.87.0
bdsf.libs/libboost_graph-c79bb0cf.so.1.87.0
bdsf.libs/libboost_numpy313-dd7ba90c.so.1.87.0
bdsf.libs/libboost_python313-cdff363f.so.1.87.0
bdsf.libs/libgfortran-040039e1.so.5.0.0
bdsf.libs/libquadmath-96973f99.so.0.0.0
bdsf-1.13.0.post2.dist-info/METADATA
bdsf-1.13.0.post2.dist-info/WHEEL
bdsf-1.13.0.post2.dist-info/entry_points.txt
bdsf-1.13.0.post2.dist-info/top_level.txt
bdsf-1.13.0.post2.dist-info/RECORD
bdsf-1.13.0.post2.dist-info/licenses/LICENSE
