Metadata-Version: 2.4
Name: bdsf
Version: 1.13.0.post2
Summary: Blob Detector and Source Finder
Author-email: David Rafferty <drafferty@hs.uni-hamburg.de>
Maintainer-email: Marcel Loose <loose@astron.nl>
License:                     GNU GENERAL PUBLIC LICENSE
Project-URL: Homepage, https://github.com/lofar-astron/PyBDSF
Project-URL: Documentation, https://pybdsf.readthedocs.io
Classifier: Development Status :: 5 - Production/Stable
Classifier: Intended Audience :: Science/Research
Classifier: Programming Language :: C++
Classifier: Programming Language :: Fortran
Classifier: Programming Language :: Python :: 3
Classifier: Programming Language :: Python :: 3.9
Classifier: Programming Language :: Python :: 3.10
Classifier: Programming Language :: Python :: 3.11
Classifier: Programming Language :: Python :: 3.12
Classifier: Programming Language :: Python :: 3.13
Classifier: Topic :: Scientific/Engineering :: Astronomy
Requires-Python: >=3.9
License-File: LICENSE
Requires-Dist: backports.shutil_get_terminal_size
Requires-Dist: astropy
Requires-Dist: numpy
Requires-Dist: scipy
Provides-Extra: ishell
Requires-Dist: ipython!=8.11.*,!=8.12.*,!=8.13.*,!=8.14.*,!=8.15.*; extra == "ishell"
Requires-Dist: matplotlib; extra == "ishell"
Dynamic: license-file
